yassm/__init__.py
yassm/config.py
yassm/main.py
yassm-0.1.7.dist-info/LICENSE
yassm-0.1.7.dist-info/METADATA
yassm-0.1.7.dist-info/WHEEL
yassm-0.1.7.dist-info/entry_points.txt
yassm-0.1.7.dist-info/top_level.txt
yassm-0.1.7.dist-info/RECORD
