Metadata-Version: 2.1
Name: yassm
Version: 0.1.7
Summary: Yet Another Simple Secrets Manager
License-File: LICENSE
Requires-Dist: Click
Requires-Dist: boto3
Requires-Dist: PyYAML
